snipsearch/__init__.py
snipsearch/cli.py
snipsearch/helper.py
snipsearch-0.0.2.dist-info/LICENSE.txt
snipsearch-0.0.2.dist-info/METADATA
snipsearch-0.0.2.dist-info/WHEEL
snipsearch-0.0.2.dist-info/entry_points.txt
snipsearch-0.0.2.dist-info/top_level.txt
snipsearch-0.0.2.dist-info/RECORD
