Metadata-Version: 2.1
Name: snipsearch
Version: 0.0.2
Summary: Python package to search multiple strings within Python snippets.
Home-page: https://github.com/jkrist2696/snipsearch
Author: Jason Krist
Author-email: jkrist2696@gmail.com
License: GNU GPLv3
Requires-Python: >=3.9
License-File: LICENSE.txt
Requires-Dist: numpy (>=1.25.0)
